pygameplus/__init__.py
pygameplus/game_object.py
pygameplus/rendering.py
pygameplus-0.0.1.dist-info/LICENSE
pygameplus-0.0.1.dist-info/METADATA
pygameplus-0.0.1.dist-info/WHEEL
pygameplus-0.0.1.dist-info/top_level.txt
pygameplus-0.0.1.dist-info/RECORD
