Metadata-Version: 2.1
Name: pygameplus
Version: 0.0.1
Summary: A small addon for pygame
Home-page: https://github.com/M1st3rButt3r/pygameplus
Author: M1st3rButt3r
Author-email: m1st3rbutt3r@gmail.com
License: UNKNOWN
Project-URL: Bug Tracker, https://github.com/M1st3rButt3r/pygameplus/issues
Platform: UNKNOWN
Classifier: Programming Language :: Python :: 3
Classifier: License :: OSI Approved :: GNU General Public License v3 (GPLv3)
Classifier: Operating System :: OS Independent
Requires-Python: >=3.6
License-File: LICENSE
Requires-Dist: pygame
